log_parser/__init__.py
log_parser/cli.py
log_parser/log_parser.py
log_parser/version.py
tests/__init__.py
tests/base.py
tests/test_log_parser.py
tests/test_version.py
common_log_parser-1.0.2.dist-info/LICENSE
common_log_parser-1.0.2.dist-info/METADATA
common_log_parser-1.0.2.dist-info/WHEEL
common_log_parser-1.0.2.dist-info/entry_points.txt
common_log_parser-1.0.2.dist-info/top_level.txt
common_log_parser-1.0.2.dist-info/RECORD
